stranger/__init__.py
stranger/__main__.py
stranger/cli.py
stranger/constants.py
stranger/utils.py
stranger/resources/__init__.py
stranger/resources/repeatexpansionsloci.tsv
stranger/resources/variant_catalog_grch37.json
stranger/resources/variant_catalog_grch38.json
stranger/resources/variant_catalog_hg19.json
stranger/resources/variant_catalog_hg38.json
stranger/resources/variant_catalog_references.json
stranger-0.10.0.dist-info/METADATA
stranger-0.10.0.dist-info/WHEEL
stranger-0.10.0.dist-info/entry_points.txt
stranger-0.10.0.dist-info/licenses/LICENSE
stranger-0.10.0.dist-info/RECORD
