Metadata-Version: 2.4
Name: stranger
Version: 0.10.0
Summary: Annotate VCF files with STR variants with pathogenicity implications
Project-URL: Repository, https://github.com/Clinical-Genomics/stranger
Project-URL: Changelog, https://github.com/Clinical-Genomics/stranger/blob/main/CHANGELOG.md
Project-URL: Bug Tracker, https://github.com/Clinical-Genomics/stranger/issues
Author-email: Daniel Nilsson <daniel.nilsson@ki.se>, Mans Magnuson <mans.magnusson@scilifelab.se>
License: MIT License
License-File: LICENSE
Keywords: str,variants,vcf
Classifier: Development Status :: 5 - Production/Stable
Classifier: Intended Audience :: Science/Research
Classifier: License :: OSI Approved :: MIT License
Classifier: Operating System :: MacOS :: MacOS X
Classifier: Operating System :: Unix
Classifier: Programming Language :: Python
Classifier: Programming Language :: Python :: 3
Classifier: Programming Language :: Python :: Implementation :: CPython
Classifier: Topic :: Scientific/Engineering :: Bio-Informatics
Classifier: Topic :: Scientific/Engineering :: Medical Science Apps.
Requires-Python: >=3.9
Requires-Dist: click
Requires-Dist: coloredlogs
Requires-Dist: importlib-resources>=5.12.0
Requires-Dist: pyyaml
